README.md
setup.py
LM_Cocktail/__init__.py
LM_Cocktail/cocktail.py
LM_Cocktail/utils.py
LM_Cocktail.egg-info/PKG-INFO
LM_Cocktail.egg-info/SOURCES.txt
LM_Cocktail.egg-info/dependency_links.txt
LM_Cocktail.egg-info/requires.txt
LM_Cocktail.egg-info/top_level.txt