Metadata-Version: 2.1
Name: LM-Cocktail
Version: 0.0.4
Summary: LM_Cocktail
Home-page: https://github.com/FlagOpen/FlagEmbedding/LM_Cocktail
Author-email: 2906698981@qq.com
